[
    {
        "question": "What was the primary characteristic of the Colosseum?",
        "A": "A gladiatorial arena",
        "B": "Built in Rome",
        "C": "A different historical event",
        "D": "A temple",
        "answer": "A",
        "funFact": "The Colosseum in Rome was a massive gladiatorial arena built in 70-80 AD. It could hold up to 80,000 spectators and hosted gladiator fights and other events."
    },
    {
        "question": "What was the primary characteristic of the Pantheon?",
        "A": "A temple in Rome",
        "B": "Has a famous dome",
        "C": "A different historical event",
        "D": "A theater",
        "answer": "A",
        "funFact": "The Pantheon in Rome is a temple with a famous dome. It was rebuilt by Hadrian and is one of the best-preserved Roman buildings."
    },
    {
        "question": "What was the primary characteristic of the Roman Forum?",
        "A": "The center of Roman public life",
        "B": "A marketplace and meeting place",
        "C": "A different historical event",
        "D": "A temple",
        "answer": "A",
        "funFact": "The Roman Forum was the center of Roman public life, serving as a marketplace, meeting place, and site of important government buildings."
    },
    {
        "question": "What was the primary characteristic of the Circus Maximus?",
        "A": "A chariot racing track",
        "B": "Could hold 250,000 people",
        "C": "A different historical event",
        "D": "A theater",
        "answer": "A",
        "funFact": "The Circus Maximus was a chariot racing track in Rome that could hold up to 250,000 people. It was the largest entertainment venue in the ancient world."
    },
    {
        "question": "What was the primary characteristic of the Appian Way?",
        "A": "A famous Roman road",
        "B": "Connected Rome to southern Italy",
        "C": "A different historical event",
        "D": "A bridge",
        "answer": "A",
        "funFact": "The Appian Way was a famous Roman road that connected Rome to southern Italy. It was one of the earliest and most important Roman roads."
    },
    {
        "question": "What was the primary characteristic of a Roman aqueduct?",
        "A": "Brought water to cities",
        "B": "Engineering marvel",
        "C": "A different historical event",
        "D": "A bridge",
        "answer": "A",
        "funFact": "Roman aqueducts brought fresh water to cities over long distances. They were engineering marvels that used gravity to transport water."
    },
    {
        "question": "What was the primary characteristic of the Pont du Gard?",
        "A": "A Roman aqueduct",
        "B": "In France",
        "C": "A different historical event",
        "D": "A bridge",
        "answer": "A",
        "funFact": "The Pont du Gard is a Roman aqueduct in France. It's one of the best-preserved Roman aqueducts and is a UNESCO World Heritage Site."
    },
    {
        "question": "What was the primary characteristic of a Roman bath?",
        "A": "A public bathing complex",
        "B": "Social center",
        "C": "A different historical event",
        "D": "A private home",
        "answer": "A",
        "funFact": "Roman baths were public bathing complexes that served as social centers. They included hot, warm, and cold pools, as well as exercise areas."
    },
    {
        "question": "What was the primary characteristic of the Baths of Caracalla?",
        "A": "A large Roman bath complex",
        "B": "In Rome",
        "C": "A different historical event",
        "D": "A temple",
        "answer": "A",
        "funFact": "The Baths of Caracalla was a large Roman bath complex in Rome. It could accommodate 1,600 bathers and was one of the largest bath complexes."
    },
    {
        "question": "What was the primary characteristic of a Roman temple?",
        "A": "Religious building",
        "B": "Dedicated to gods",
        "C": "A different historical event",
        "D": "A theater",
        "answer": "A",
        "funFact": "Roman temples were religious buildings dedicated to gods. They were based on Greek temple designs but had distinct Roman features."
    },
    {
        "question": "What was the primary characteristic of the Temple of Jupiter?",
        "A": "On the Capitoline Hill",
        "B": "Most important temple",
        "C": "A different historical event",
        "D": "In the Forum",
        "answer": "A",
        "funFact": "The Temple of Jupiter Optimus Maximus was on the Capitoline Hill in Rome and was the most important temple. It was dedicated to Jupiter, Juno, and Minerva."
    },
    {
        "question": "What was the primary characteristic of a Roman theater?",
        "A": "For plays and performances",
        "B": "Semicircular design",
        "C": "A different historical event",
        "D": "Round design",
        "answer": "A",
        "funFact": "Roman theaters were for plays and performances and had a semicircular design. They were based on Greek theaters but had distinct Roman features."
    },
    {
        "question": "What was the primary characteristic of a Roman amphitheater?",
        "A": "For gladiator fights",
        "B": "Oval or circular",
        "C": "A different historical event",
        "D": "Semicircular",
        "answer": "A",
        "funFact": "Roman amphitheaters were for gladiator fights and had an oval or circular design. The Colosseum is the most famous example."
    },
    {
        "question": "What was the primary characteristic of a Roman basilica?",
        "A": "A public building",
        "B": "Used for law and business",
        "C": "A different historical event",
        "D": "A temple",
        "answer": "A",
        "funFact": "A Roman basilica was a public building used for law courts and business. The design influenced later Christian churches."
    },
    {
        "question": "What was the primary characteristic of a Roman villa?",
        "A": "A country house",
        "B": "For wealthy Romans",
        "C": "A different historical event",
        "D": "A city apartment",
        "answer": "A",
        "funFact": "A Roman villa was a country house for wealthy Romans. Villas were often large estates with farms, gardens, and luxurious accommodations."
    },
    {
        "question": "What was the primary characteristic of a Roman insula?",
        "A": "An apartment building",
        "B": "For common people",
        "C": "A different historical event",
        "D": "A villa",
        "answer": "A",
        "funFact": "A Roman insula was an apartment building for common people in cities. They were often poorly built and prone to fires and collapses."
    },
    {
        "question": "What was the primary characteristic of Roman concrete?",
        "A": "Revolutionary building material",
        "B": "Allowed large structures",
        "C": "A different historical event",
        "D": "Weak",
        "answer": "A",
        "funFact": "Roman concrete was a revolutionary building material that allowed the construction of large structures like the Pantheon's dome. It's still studied today."
    },
    {
        "question": "What was the primary characteristic of a Roman arch?",
        "A": "Architectural feature",
        "B": "Allowed larger buildings",
        "C": "A different historical event",
        "D": "Decorative only",
        "answer": "A",
        "funFact": "The Roman arch was an architectural feature that allowed the construction of larger buildings. Arches distributed weight effectively and were used in many structures."
    },
    {
        "question": "What was the primary characteristic of a Roman dome?",
        "A": "Architectural feature",
        "B": "Used in the Pantheon",
        "C": "A different historical event",
        "D": "Decorative only",
        "answer": "A",
        "funFact": "The Roman dome was an architectural feature used in buildings like the Pantheon. The Pantheon's dome is still the largest unreinforced concrete dome in the world."
    },
    {
        "question": "What was the primary characteristic of the legacy of Roman buildings?",
        "A": "Influenced architecture for centuries",
        "B": "Many still stand today",
        "C": "A different historical event",
        "D": "Forgotten",
        "answer": "A",
        "funFact": "Roman buildings influenced architecture for centuries, and many still stand today. Roman architectural techniques are still used in modern construction."
    }
]